[
    {"id": "root", "name": "TTX", "tid": ""},
    {"id": "user", "name": "User", "tid": "ttx.dijit.wso.Bill", "oid": "user", "parent": "root"},
    {"id": "creation", "name": "Creation", "tid": "ttx.dijit.wso.Creation", "oid": "*", "parent": "root"},
    {"id": "basis", "name": "Basis Data", "parent": "root"},
    {"id": "basis_general", "name": "General", "parent": "basis"},
    {"id": "owner", "name": "Owner", "tid": "", "parent": "basis_general"},
    {"id": "material", "name": "物料", "tid": "", "parent": "basis_general"},
    {"id": "basis_wms", "name": "仓储", "tid": "", "parent": "basis"},
    {"id": "storeroom", "name": "仓间", "tid": "", "parent": "basis_wms"},
    {"id": "storearea", "name": "库区", "tid": "", "parent": "basis_wms"},
    {"id": "location", "name": "储位", "tid": "continent", "parent": "basis_wms"},
    {"id": "inbound", "name": "入库", "tid": "", "parent": "root"},
    {"id": "receipt", "name": "入库单", "tid": "", "parent": "inbound"},
    {"id": "outbound", "name": "出库", "tid": "", "parent": "root"},
    {"id": "shipment", "name": "出库单", "tid": "", "parent": "outbound"}
]